cellphe/__init__.py
cellphe/classification.py
cellphe/clustering.py
cellphe/imagej.py
cellphe/input.py
cellphe/separation.py
cellphe/trackmate.py
cellphe/features/__init__.py
cellphe/features/frame.py
cellphe/features/helpers.py
cellphe/features/time_series.py
cellphe/processing/__init__.py
cellphe/processing/image.py
cellphe/processing/roi.py
cellphe/segmentation/__init__.py
cellphe/segmentation/seg_errors.py
cellphe-0.4.4.dist-info/licenses/LICENSE
cellphe-0.4.4.dist-info/WHEEL
cellphe-0.4.4.dist-info/METADATA
cellphe-0.4.4.dist-info/RECORD
