Metadata-Version: 2.4
Name: cellphe
Version: 0.4.4
Summary: CellPhe: Toolkit for cell phenotyping from time-lapse videos
Author-email: Stuart Lacy <stuart.lacy@york.ac.uk>, Laura Wiggins <l.wiggins@sheffield.ac.uk>
Requires-Python: >=3.8.1
Classifier: Development Status :: 3 - Alpha
Classifier: Intended Audience :: Developers
Classifier: License :: OSI Approved :: MIT License
Classifier: Programming Language :: Python :: 3 :: Only
Classifier: Programming Language :: Python :: 3.8
Classifier: Programming Language :: Python :: 3.9
Classifier: Programming Language :: Python :: 3.10
Classifier: Programming Language :: Python :: 3.11
Classifier: Programming Language :: Python :: 3.12
License-File: LICENSE
Requires-Dist: cellpose==3.1.1.2
Requires-Dist: imbalanced-learn
Requires-Dist: JPype1==1.5.2
Requires-Dist: matplotlib
Requires-Dist: numpy
Requires-Dist: pandas
Requires-Dist: pillow
Requires-Dist: pyimagej
Requires-Dist: pyjanitor
Requires-Dist: pywavelets
Requires-Dist: roifile
Requires-Dist: scipy
Requires-Dist: scikit-image
Requires-Dist: scikit-learn
Requires-Dist: shapely==2.0.7
Requires-Dist: xgboost
Requires-Dist: pyspark>=3.0.0 ; extra == "spark"
Requires-Dist: bandit[toml]==1.8.6 ; extra == "test"
Requires-Dist: black==25.1.0 ; extra == "test"
Requires-Dist: check-manifest==0.50 ; extra == "test"
Requires-Dist: flake8-bugbear==24.12.12 ; extra == "test"
Requires-Dist: flake8-docstrings ; extra == "test"
Requires-Dist: flake8-formatter_junit_xml ; extra == "test"
Requires-Dist: flake8 ; extra == "test"
Requires-Dist: flake8-pyproject ; extra == "test"
Requires-Dist: pre-commit==4.3.0 ; extra == "test"
Requires-Dist: pylint==3.3.8 ; extra == "test"
Requires-Dist: pylint_junit ; extra == "test"
Requires-Dist: pytest-cov==6.2.1 ; extra == "test"
Requires-Dist: pytest-mock<3.15.1 ; extra == "test"
Requires-Dist: pytest-runner ; extra == "test"
Requires-Dist: pytest==8.4.2 ; extra == "test"
Requires-Dist: pytest-github-actions-annotate-failures ; extra == "test"
Requires-Dist: shellcheck-py==0.11.0.1 ; extra == "test"
Project-URL: Documentation, https://uoy-research.github.io/CellPhePy
Project-URL: Source, https://github.com/uoy-research/CellPhePy/issues
Project-URL: Tracker, https://github.com/uoy-research/CellPhePy
Provides-Extra: spark
Provides-Extra: test
